{
   "status":"OK",
   "copyright":"Copyright (c) 2017 Pro Publica Inc. All Rights Reserved.",
   "results":[
      {
         "member_id": "M001144",
         
         "first_name": "Jeff",
         "middle_name": null,
         "last_name": "Miller",
         "date_of_birth": "1959-06-27",
         "gender": "M",
         "url": null,
         "times_topics_url": "",
         "times_tag": "",
         "govtrack_id": "400279",
         "cspan_id": "91615",
         "votesmart_id": null,
         "icpsr_id": "20110",
         "twitter_account": null,
         "facebook_account": "RepJeffMiller",
         "youtube_account": "RepJeffMiller",
         "crp_id": null,
         "google_entity_id": "/m/0251vm",
         "rss_url": "http://jeffmiller.house.gov/news/rss.aspx",
         "in_office": false,
         "current_party": "R",
         "most_recent_vote": "2016-12-08",
         "roles": [
 {
           "congress": "114",
           "chamber": "House",
           "title": "Representative",
           "state": "FL",
           "party": "R",
           "leadership_role": null,
           "fec_candidate_id": "H2FL01100",
           "seniority": "16",
           "district": "1", "at_large": false,
           "ocd_id": "ocd-division/country:us/state:fl/cd:1",
           "start_date": "2015-01-06",
           "end_date": "2017-01-03",
           "office": null,
           "phone": null,
           "fax": null,
           "contact_form": null,
           "bills_sponsored": 40,
           "bills_cosponsored": 263,
           "missed_votes_pct": 3.17,
           "votes_with_party_pct": 95.09,
           "committees": [
           {
             "name": "Committee on Armed Services",
             "code": "HSAS",
             "api_uri": "https://api.propublica.org/congress/v1/114/house/committees/HSAS.json",
             "rank_in_party": 4,
             "begin_date": "",
             "end_date": "2017-01-03"
           },
           {
             "name": "Permanent Select Committee on Intelligence",
             "code": "HSIG",
             "api_uri": "https://api.propublica.org/congress/v1/114/house/committees/HSIG.json",
             "rank_in_party": 2,
             "begin_date": "",
             "end_date": "2017-01-03"
           },
           {
             "name": "Committee on Veterans&#39; Affairs",
             "code": "HSVR",
             "api_uri": "https://api.propublica.org/congress/v1/114/house/committees/HSVR.json",
             "rank_in_party": 1,
             "begin_date": "",
             "end_date": "2017-01-03"
           }
           ],
           "subcommittees": [
           ]
         },
        {
           "congress": "113",
           "chamber": "House",
           "title": "Representative",
           "state": "FL",
           "party": "R",
           "leadership_role": null,
           "fec_candidate_id": "",
           "seniority": "14",
           "district": "1", "at_large": false,
           "ocd_id": "ocd-division/country:us/state:fl/cd:1",
           "start_date": "2013-01-03",
           "end_date": "2015-01-02",
           "office": null,
           "phone": null,
           "fax": null,
           "contact_form": null,
           "bills_sponsored": 28,
           "bills_cosponsored": 270,
           "missed_votes_pct": 5.29,
           "votes_with_party_pct": 93.36,
           "committees": [
           {
             "name": "Permanent Select Committee on Intelligence",
             "code": "HSIG",
             "api_uri": "https://api.propublica.org/congress/v1/113/house/committees/HSIG.json",
             "rank_in_party": 3,
             "begin_date": "2013-02-08",
             "end_date": "2015-01-03"
           },
           {
             "name": "Committee on Armed Services",
             "code": "HSAS",
             "api_uri": "https://api.propublica.org/congress/v1/113/house/committees/HSAS.json",
             "rank_in_party": 5,
             "begin_date": "2013-01-04",
             "end_date": "2015-01-03"
           },
           {
             "name": "Committee on Veterans&#39; Affairs",
             "code": "HSVR",
             "api_uri": "https://api.propublica.org/congress/v1/113/house/committees/HSVR.json",
             "rank_in_party": 1,
             "begin_date": "2013-01-03",
             "end_date": "2015-01-03"
           }
           ],
           "subcommittees": [
           ]
         },
        {
           "congress": "112",
           "chamber": "House",
           "title": "Representative",
           "state": "FL",
           "party": "R",
           "leadership_role": null,
           "fec_candidate_id": "",
           "seniority": "12",
           "district": "1", "at_large": false,
           "ocd_id": "ocd-division/country:us/state:fl/cd:1",
           "start_date": "2011-01-04",
           "end_date": "2013-01-03",
           "office": null,
           "phone": null,
           "fax": null,
           "contact_form": null,
           "bills_sponsored": 21,
           "bills_cosponsored": 337,
           "missed_votes_pct": 2.99,
           "votes_with_party_pct": 92.11,
           "committees": [
           {
             "name": "Committee on Armed Services",
             "code": "HSAS",
             "api_uri": "https://api.propublica.org/congress/v1/112/house/committees/HSAS.json",
             "rank_in_party": 7,
             "begin_date": "2011-01-12",
             "end_date": "2013-01-03"
           },
           {
             "name": "Permanent Select Committee on Intelligence",
             "code": "HSIG",
             "api_uri": "https://api.propublica.org/congress/v1/112/house/committees/HSIG.json",
             "rank_in_party": 4,
             "begin_date": "2011-01-12",
             "end_date": "2013-01-03"
           },
           {
             "name": "Committee on Veterans&#39; Affairs",
             "code": "HSVR",
             "api_uri": "https://api.propublica.org/congress/v1/112/house/committees/HSVR.json",
             "rank_in_party": 1,
             "begin_date": "2011-01-05",
             "end_date": "2013-01-03"
           }
           ],
           "subcommittees": [
           ]
         },
        {
           "congress": "111",
           "chamber": "House",
           "title": "Representative",
           "state": "FL",
           "party": "R",
           "leadership_role": null,
           "fec_candidate_id": "",
           "seniority": "10",
           "district": "1", "at_large": false,
           "ocd_id": "ocd-division/country:us/state:fl/cd:1",
           "start_date": "2009-01-06",
           "end_date": "2011-01-03",
           "office": null,
           "phone": null,
           "fax": null,
           "contact_form": null,
           "bills_sponsored": 7,
           "bills_cosponsored": 380,
           "missed_votes_pct": 2.36,
           "votes_with_party_pct": 94.17,
           "committees": [
           {
             "name": "Permanent Select Committee on Intelligence",
             "code": "HSIG",
             "api_uri": "https://api.propublica.org/congress/v1/111/house/committees/HSIG.json",
             "rank_in_party": 7,
             "begin_date": "2009-02-04",
             "end_date": "2011-01-03"
           },
           {
             "name": "Committee on Veterans&#39; Affairs",
             "code": "HSVR",
             "api_uri": "https://api.propublica.org/congress/v1/111/house/committees/HSVR.json",
             "rank_in_party": 5,
             "begin_date": "2009-01-09",
             "end_date": "2011-01-03"
           },
           {
             "name": "Committee on Armed Services",
             "code": "HSAS",
             "api_uri": "https://api.propublica.org/congress/v1/111/house/committees/HSAS.json",
             "rank_in_party": 7,
             "begin_date": "2009-01-09",
             "end_date": "2011-01-03"
           }
           ],
           "subcommittees": [
           ]
         },
        {
           "congress": "110",
           "chamber": "House",
           "title": "Representative",
           "state": "FL",
           "party": "R",
           "leadership_role": null,
           "fec_candidate_id": "",
           "seniority": "8",
           "district": "1", "at_large": false,
           "ocd_id": "ocd-division/country:us/state:fl/cd:1",
           "start_date": "2007-01-04",
           "end_date": "2009-01-03",
           "office": null,
           "phone": null,
           "fax": null,
           "contact_form": null,
           "bills_sponsored": 15,
           "bills_cosponsored": 529,
           "missed_votes_pct": 4.59,
           "votes_with_party_pct": 90.11,
           "committees": [
           {
             "name": "Committee on Armed Services",
             "code": "HSAS",
             "api_uri": "https://api.propublica.org/congress/v1/110/house/committees/HSAS.json",
             "rank_in_party": 11,
             "begin_date": "2007-01-10",
             "end_date": "2009-01-03"
           },
           {
             "name": "Committee on Veterans&#39; Affairs",
             "code": "HSVR",
             "api_uri": "https://api.propublica.org/congress/v1/110/house/committees/HSVR.json",
             "rank_in_party": 7,
             "begin_date": "2007-01-10",
             "end_date": "2009-01-03"
           }
           ],
           "subcommittees": [
           ]
         },
        {
           "congress": "109",
           "chamber": "House",
           "title": "Representative",
           "state": "FL",
           "party": "R",
           "leadership_role": null,
           "fec_candidate_id": "",
           "seniority": "6",
           "district": "1", "at_large": false,
           "ocd_id": "ocd-division/country:us/state:fl/cd:1",
           "start_date": "2005-01-04",
           "end_date": "2007-01-03",
           "office": null,
           "phone": null,
           "fax": null,
           "contact_form": null,
           "bills_sponsored": 16,
           "bills_cosponsored": 477,
           "missed_votes_pct": 4.37,
           "votes_with_party_pct": 89.66,
           "committees": [
],
           "subcommittees": [
]
         },
        {
           "congress": "108",
           "chamber": "House",
           "title": "Representative",
           "state": "FL",
           "party": "R",
           "leadership_role": null,
           "fec_candidate_id": "",
           "seniority": "4",
           "district": "1", "at_large": false,
           "ocd_id": "ocd-division/country:us/state:fl/cd:1",
           "start_date": "2003-01-07",
           "end_date": "2005-01-03",
           "office": null,
           "phone": null,
           "fax": null,
           "contact_form": null,
           "bills_sponsored": 14,
           "bills_cosponsored": 356,
           "missed_votes_pct": 5.65,
           "votes_with_party_pct": 89.93,
           "committees": [
],
           "subcommittees": [
]
         },
        {
           "congress": "107",
           "chamber": "House",
           "title": "Representative",
           "state": "FL",
           "party": "R",
           "leadership_role": null,
           "fec_candidate_id": "",
           "seniority": "2",
           "district": "1", "at_large": false,
           "ocd_id": "ocd-division/country:us/state:fl/cd:1",
           "start_date": "2001-01-03",
           "end_date": "2003-01-03",
           "office": null,
           "phone": null,
           "fax": null,
           "contact_form": null,
           "bills_sponsored": 6,
           "bills_cosponsored": 107,
           "missed_votes_pct": 1.83,
           "votes_with_party_pct": 93.56,
           "committees": [
],
           "subcommittees": [
]
         }
       ]
        }
    ]
}
